MANIFEST.in
README.md
setup.py
sound_search.py
tonescale.py
tonescale.egg-info/PKG-INFO
tonescale.egg-info/SOURCES.txt
tonescale.egg-info/dependency_links.txt
tonescale.egg-info/entry_points.txt
tonescale.egg-info/requires.txt
tonescale.egg-info/top_level.txt