Metadata-Version: 1.0
Name: tonescale
Version: 2018.2.6.1919
Summary: sound utilities and sounds
Home-page: https://github.com/wdbm/tonescale
Author: Will Breaden Madden
Author-email: wbm@protonmail.ch
License: GPLv3
Platform: UNKNOWN
